[
    {
        "image": "engagement1.jpeg",
        "alt": "Engagement 1"
    },
    {
        "image": "engagement2.jpeg",
        "alt": "Engagement 2"
    },
    {
        "image": "engagement3.jpeg",
        "alt": "Engagement 3"
    },
    {
        "image": "engagement4.jpeg",
        "alt": "Engagement 4"
    },
    {
        "image": "engagement5.jpeg",
        "alt": "Engagement 5"
    },
    {
        "image": "engagement6.jpeg",
        "alt": "Engagement 6"
    },
    {
        "image": "engagement7.jpeg",
        "alt": "Engagement 7"
    },
    {
        "image": "engagement8.jpeg",
        "alt": "Engagement 8"
    },
    {
        "image": "engagement9.jpeg",
        "alt": "Engagement 9"
    },
    {
        "image": "engagement10.jpeg",
        "alt": "Engagement 10"
    },
    {
        "image": "engagement11.jpeg",
        "alt": "Engagement 11"
    },
    {
        "image": "engagement12.jpeg",
        "alt": "Engagement 12"
    },
    {
        "image": "engagement13.jpeg",
        "alt": "Engagement 13"
    },
    {
        "image": "engagement14.jpeg",
        "alt": "Engagement 14"
    },
    {
        "image": "engagement15.jpeg",
        "alt": "Engagement 15"
    },
    {
        "image": "engagement16.jpeg",
        "alt": "Engagement 16"
    },
    {
        "image": "engagement17.jpeg",
        "alt": "Engagement 17"
    },
    {
        "image": "engagement18.jpeg",
        "alt": "Engagement 18"
    },
    {
        "image": "engagement19.jpeg",
        "alt": "Engagement 19"
    },
    {
        "image": "engagement20.jpeg",
        "alt": "Engagement 20"
    },
    {
        "image": "engagement21.jpeg",
        "alt": "Engagement 21"
    },
    {
        "image": "engagement22.jpeg",
        "alt": "Engagement 22"
    },
    {
        "image": "engagement23.jpeg",
        "alt": "Engagement 23"
    },
    {
        "image": "engagement24.jpeg",
        "alt": "Engagement 24"
    }
]
